Changelog
MANIFEST.in
README
distribute-0.6.30.tar.gz
distribute_setup.py
setup.py
bin/tl
bin/tl-fleet
bin/tl-irc
bin/tl-xmpp
tl/__init__.py
tl/id.py
tl/imports.py
tl/memcached.py
tl/path.py
tl/version.py
tl.egg-info/PKG-INFO
tl.egg-info/SOURCES.txt
tl.egg-info/dependency_links.txt
tl.egg-info/not-zip-safe
tl.egg-info/top_level.txt
tl/api/__init__.py
tl/api/hooks.py
tl/api/server.py
tl/contrib/__init__.py
tl/contrib/feedparser.py
tl/contrib/irccrypt.py
tl/contrib/memcache.py
tl/contrib/rijndael.py
tl/contrib/sgmllib.py
tl/contrib/sgmllib3.py
tl/contrib/bs4/__init__.py
tl/contrib/bs4/dammit.py
tl/contrib/bs4/element.py
tl/contrib/bs4/testing.py
tl/contrib/bs4/builder/__init__.py
tl/contrib/bs4/builder/_html5lib.py
tl/contrib/bs4/builder/_htmlparser.py
tl/contrib/bs4/builder/_lxml.py
tl/contrib/natural/__init__.py
tl/contrib/natural/constant.py
tl/contrib/natural/data.py
tl/contrib/natural/date.py
tl/contrib/natural/file.py
tl/contrib/natural/number.py
tl/contrib/natural/size.py
tl/contrib/natural/text.py
tl/contrib/natural/locale/af_ZA/LC_MESSAGES/natural.mo
tl/contrib/natural/locale/de_DE/LC_MESSAGES/natural.mo
tl/contrib/natural/locale/en_GB/LC_MESSAGES/natural.mo
tl/contrib/natural/locale/en_US/LC_MESSAGES/natural.mo
tl/contrib/natural/locale/es_ES/LC_MESSAGES/natural.mo
tl/contrib/natural/locale/fr_FR/LC_MESSAGES/natural.mo
tl/contrib/natural/locale/nl_NL/LC_MESSAGES/natural.mo
tl/contrib/natural/templatetags/__init__.py
tl/contrib/natural/templatetags/naturalise.py
tl/contrib/natural/templatetags/naturalize.py
tl/contrib/sleekxmpp/__init__.py
tl/contrib/sleekxmpp/basexmpp.py
tl/contrib/sleekxmpp/clientxmpp.py
tl/contrib/sleekxmpp/componentxmpp.py
tl/contrib/sleekxmpp/exceptions.py
tl/contrib/sleekxmpp/version.py
tl/contrib/sleekxmpp/features/__init__.py
tl/contrib/sleekxmpp/features/feature_bind/__init__.py
tl/contrib/sleekxmpp/features/feature_bind/bind.py
tl/contrib/sleekxmpp/features/feature_bind/stanza.py
tl/contrib/sleekxmpp/features/feature_mechanisms/__init__.py
tl/contrib/sleekxmpp/features/feature_mechanisms/mechanisms.py
