Metadata-Version: 1.1
Name: tl
Version: 0.4.3
Summary: T I M E L I N E
Home-page: https://github.com/feedbackflow/tl
Author: Bart Thate
Author-email: feedbackflow@gmail.com
License: MIT
Platform: UNKNOWN
Classifier: Development Status :: 3 - Alpha
Classifier: Environment :: Console
Classifier: Environment :: Other Environment
Classifier: Intended Audience :: Developers
Classifier: License :: OSI Approved :: MIT License
Classifier: Operating System :: Unix
Classifier: Programming Language :: Python
Classifier: Topic :: Communications :: Chat
Classifier: Topic :: Software Development :: Libraries :: Python Modules
Requires: distribute
